smart_calculator/__init__.py
smart_calculator/__main__.py
smart_calculator/main.py
smart_calculator-0.3.1.dist-info/METADATA
smart_calculator-0.3.1.dist-info/WHEEL
smart_calculator-0.3.1.dist-info/entry_points.txt
smart_calculator-0.3.1.dist-info/top_level.txt
smart_calculator-0.3.1.dist-info/RECORD
