Metadata-Version: 2.2
Name: smart_calculator
Version: 0.3.1
Author: Chukwunonso Smart Agbawo
Author-email: chukwunonsosmartagbawo@gmail.com
Maintainer: Chukwunonso Smart Agbawo
Maintainer-email: chukwunonsosmartagbawo@gmail.com
Dynamic: author
Dynamic: author-email
Dynamic: description
Dynamic: description-content-type
Dynamic: maintainer
Dynamic: maintainer-email
